WeiXueyuanQianrushiJiaochengFix1/README.md
WeiXueyuanQianrushiJiaochengFix1/__init__.py
WeiXueyuanQianrushiJiaochengFix1/__main__.py
WeiXueyuanQianrushiJiaochengFix1/file.epub
WeiXueyuanQianrushiJiaochengFix1/index.html
WeiXueyuanQianrushiJiaochengFix1/css/__init__.py
WeiXueyuanQianrushiJiaochengFix1/css/annotations.css
WeiXueyuanQianrushiJiaochengFix1/css/main.css
WeiXueyuanQianrushiJiaochengFix1/css/normalize.css
WeiXueyuanQianrushiJiaochengFix1/css/popup.css
WeiXueyuanQianrushiJiaochengFix1/font/__init__.py
WeiXueyuanQianrushiJiaochengFix1/font/fontello.eot
WeiXueyuanQianrushiJiaochengFix1/font/fontello.svg
WeiXueyuanQianrushiJiaochengFix1/font/fontello.ttf
WeiXueyuanQianrushiJiaochengFix1/font/fontello.woff
WeiXueyuanQianrushiJiaochengFix1/img/__init__.py
WeiXueyuanQianrushiJiaochengFix1/img/annotator-glyph-sprite.png
WeiXueyuanQianrushiJiaochengFix1/img/annotator-icon-sprite.png
WeiXueyuanQianrushiJiaochengFix1/img/apple-touch-icon.png
WeiXueyuanQianrushiJiaochengFix1/img/cancelfullscreen.png
WeiXueyuanQianrushiJiaochengFix1/img/close.png
WeiXueyuanQianrushiJiaochengFix1/img/fullscreen.png
WeiXueyuanQianrushiJiaochengFix1/img/loader.gif
WeiXueyuanQianrushiJiaochengFix1/img/menu-icon.png
WeiXueyuanQianrushiJiaochengFix1/img/save.png
WeiXueyuanQianrushiJiaochengFix1/img/saved.png
WeiXueyuanQianrushiJiaochengFix1/img/settings-s.png
WeiXueyuanQianrushiJiaochengFix1/img/settings.png
WeiXueyuanQianrushiJiaochengFix1/img/star.png
WeiXueyuanQianrushiJiaochengFix1/js/__init__.py
WeiXueyuanQianrushiJiaochengFix1/js/epub.js
WeiXueyuanQianrushiJiaochengFix1/js/epub.min.js
WeiXueyuanQianrushiJiaochengFix1/js/epub.min.map
WeiXueyuanQianrushiJiaochengFix1/js/hooks.min.js
WeiXueyuanQianrushiJiaochengFix1/js/hooks.min.map
WeiXueyuanQianrushiJiaochengFix1/js/reader.js
WeiXueyuanQianrushiJiaochengFix1/js/reader.js.map
WeiXueyuanQianrushiJiaochengFix1/js/reader.min.js
WeiXueyuanQianrushiJiaochengFix1/js/reader.min.map
WeiXueyuanQianrushiJiaochengFix1/js/hooks/__init__.py
wei_xueyuan_qianrushi_jiaocheng_fix1-2025.3.25.0.dist-info/METADATA
wei_xueyuan_qianrushi_jiaocheng_fix1-2025.3.25.0.dist-info/WHEEL
wei_xueyuan_qianrushi_jiaocheng_fix1-2025.3.25.0.dist-info/entry_points.txt
wei_xueyuan_qianrushi_jiaocheng_fix1-2025.3.25.0.dist-info/top_level.txt
wei_xueyuan_qianrushi_jiaocheng_fix1-2025.3.25.0.dist-info/RECORD
